gymnasium_env/__init__.py
gymnasium_env/envs/__init__.py
gymnasium_env/envs/drone_tsp.py
gymnasium_env/envs/folium_exporter.py
gymnasium_env/envs/interfaces.py
gymnasium_env/envs/node_transformer.py
gymnasium_env/envs/utils.py
gymnasium_env/wrappers/__init__.py
gymnasium_env/wrappers/clip_reward.py
gymnasium_env/wrappers/discrete_actions.py
gymnasium_env/wrappers/reacher_weighted_reward.py
gymnasium_env/wrappers/relative_position.py
dronetsp-1.0.2.dist-info/METADATA
dronetsp-1.0.2.dist-info/WHEEL
dronetsp-1.0.2.dist-info/licenses/LICENSE
dronetsp-1.0.2.dist-info/RECORD
