Metadata-Version: 2.4
Name: DroneTSP
Version: 1.0.2
Summary: Drone TSP Gymnasium environment and wrappers
Author-email: Trương Hải Đăng <haidanghth910@gmail.com>
License: The MIT License
License-File: LICENSE
Keywords: drone,environment,gymnasium,reinforcement-learning,tsp
Classifier: Development Status :: 4 - Beta
Classifier: Intended Audience :: Science/Research
Classifier: License :: OSI Approved :: MIT License
Classifier: Operating System :: OS Independent
Classifier: Programming Language :: Python
Classifier: Programming Language :: Python :: 3
Classifier: Topic :: Scientific/Engineering :: Artificial Intelligence
Requires-Python: >=3.8
Requires-Dist: folium
Requires-Dist: geopy
Requires-Dist: gymnasium
Requires-Dist: numpy
Provides-Extra: dev
Requires-Dist: build; extra == 'dev'
Requires-Dist: pre-commit; extra == 'dev'
Requires-Dist: twine; extra == 'dev'
